buildbot_UnrealEngine/__init__.py
buildbot_UnrealEngine/AutomationTool/BuildCookRun.py
buildbot_UnrealEngine/AutomationTool/__init__.py
buildbot_UnrealEngine/BuildTool/Build.py
buildbot_UnrealEngine/BuildTool/__init__.py
buildbot_UnrealEngine/UnrealCommand/BaseUnrealCommand.py
buildbot_UnrealEngine/UnrealCommand/__init__.py
buildbot_UnrealEngine-1.7.1.dist-info/LICENSE
buildbot_UnrealEngine-1.7.1.dist-info/METADATA
buildbot_UnrealEngine-1.7.1.dist-info/WHEEL
buildbot_UnrealEngine-1.7.1.dist-info/entry_points.txt
buildbot_UnrealEngine-1.7.1.dist-info/top_level.txt
buildbot_UnrealEngine-1.7.1.dist-info/RECORD
