Metadata-Version: 2.1
Name: buildbot-UnrealEngine
Version: 1.7.1
Summary: Easy configuration for the Unreal Automation Tool
Home-page: https://github.com/pampersrocker/buildbot-UnrealEngine
Author: Marvin Pohl
Author-email: marvin@lab132.com
License: UNKNOWN
Platform: UNKNOWN
Classifier: Development Status :: 5 - Production/Stable
Classifier: Environment :: Plugins
Classifier: Intended Audience :: Developers
Classifier: License :: OSI Approved :: MIT License
Classifier: Operating System :: Microsoft :: Windows
Classifier: Operating System :: MacOS
Classifier: Operating System :: POSIX :: Linux
Classifier: Programming Language :: C++
Classifier: Programming Language :: Python :: 2.7
Classifier: Topic :: Software Development :: Build Tools
Requires: Buildbot (>=2.2.0)
